sentry_notice/__init__.py
sentry_notice/forms.py
sentry_notice/plugin.py
sentry_notice-1.0.4.dist-info/METADATA
sentry_notice-1.0.4.dist-info/WHEEL
sentry_notice-1.0.4.dist-info/entry_points.txt
sentry_notice-1.0.4.dist-info/top_level.txt
sentry_notice-1.0.4.dist-info/RECORD
