Metadata-Version: 2.1
Name: sentry-notice
Version: 1.0.4
Summary: sentry 接入dingTalk 告警
Home-page: https://github.com/spxinjie6/sentry-notice.git
Author: spxinjie6
Author-email: 1311855817@qq.com
License: MIT
Keywords: python sentry dingTalk notice
Platform: UNKNOWN
Classifier: Programming Language :: Python :: 3
Classifier: License :: OSI Approved :: MIT License
Requires-Dist: requests
